juham_homewizard/__init__.py
juham_homewizard/homewizard_plugin.py
juham_homewizard/homewizardwatermeter.py
juham_homewizard/py.typed
juham_homewizard-0.1.0.dist-info/licenses/LICENSE.rst
juham_homewizard-0.1.0.dist-info/METADATA
juham_homewizard-0.1.0.dist-info/WHEEL
juham_homewizard-0.1.0.dist-info/entry_points.txt
juham_homewizard-0.1.0.dist-info/top_level.txt
juham_homewizard-0.1.0.dist-info/RECORD
